README.rst
setup.py
order_of_magnitude/__init__.py
order_of_magnitude/order_of_magnitude.py
order_of_magnitude.egg-info/PKG-INFO
order_of_magnitude.egg-info/SOURCES.txt
order_of_magnitude.egg-info/dependency_links.txt
order_of_magnitude.egg-info/top_level.txt