Metadata-Version: 2.1
Name: order-of-magnitude
Version: 2.1
Summary: Converts floats to SI units.
Home-page: https://github.com/Tioz90/order_of_magnitude
Author: Thomas Tiotto
Author-email: tioz1990@gmail.com
License: MIT
Platform: UNKNOWN
